imagenet_x/__init__.py
imagenet_x/__main__.py
imagenet_x/aggregate.py
imagenet_x/check_prototypes.py
imagenet_x/evaluate.py
imagenet_x/model_types.py
imagenet_x/plots.py
imagenet_x/prevalence.py
imagenet_x/utils.py
imagenet_x/annotations/filename_label.csv
imagenet_x/annotations/imagenet_1k_classes_to_100_metaclasses.csv
imagenet_x/annotations/imagenet_labels.txt
imagenet_x/annotations/imagenet_real_labels.jsonl
imagenet_x/annotations/imagenet_x_train_multi_factor.jsonl
imagenet_x/annotations/imagenet_x_train_top_factor.jsonl
imagenet_x/annotations/imagenet_x_val_multi_factor.jsonl
imagenet_x/annotations/imagenet_x_val_top_factor.jsonl
imagenet_x/annotations/prototypical_paths.csv
imagenet_x-0.0.7.dist-info/LICENSE
imagenet_x-0.0.7.dist-info/METADATA
imagenet_x-0.0.7.dist-info/WHEEL
imagenet_x-0.0.7.dist-info/top_level.txt
imagenet_x-0.0.7.dist-info/zip-safe
imagenet_x-0.0.7.dist-info/RECORD
