Metadata-Version: 2.1
Name: imagenet-x
Version: 0.0.7
Summary: Imagenet factors of variation annotations
Home-page: https://fb.me/imagenetx
Author: Badr Youbi Idrissi, Mark Ibrahim
Author-email: byoubi@meta.com, marksibrahim@meta.com
License: BSD 3-Clause License
Keywords: imagenet,robustness,deep learning
Classifier: Programming Language :: Python :: 3
License-File: LICENSE
Requires-Dist: pandas
Requires-Dist: scipy
Requires-Dist: tqdm
Requires-Dist: importlib-resources ; python_version < "3.9"
Provides-Extra: all
Requires-Dist: matplotlib ; extra == 'all'
Requires-Dist: plotly ; extra == 'all'
Requires-Dist: tabulate ; extra == 'all'
Requires-Dist: seaborn ; extra == 'all'
Requires-Dist: scipy (>=1.7.0) ; extra == 'all'
Requires-Dist: jinja2 ; extra == 'all'
Requires-Dist: torch ; extra == 'all'
Requires-Dist: torchvision ; extra == 'all'
